pymatviz/.DS_Store
pymatviz/__init__.py
pymatviz/bar.py
pymatviz/brillouin.py
pymatviz/chem_env.py
pymatviz/classify/__init__.py
pymatviz/classify/confusion_matrix.py
pymatviz/classify/curves.py
pymatviz/cluster/__init__.py
pymatviz/cluster/composition/__init__.py
pymatviz/cluster/composition/embed.py
pymatviz/cluster/composition/plot.py
pymatviz/cluster/composition/project.py
pymatviz/colors.py
pymatviz/coordination/__init__.py
pymatviz/coordination/figures.py
pymatviz/coordination/helpers.py
pymatviz/data/__init__.py
pymatviz/elements.csv
pymatviz/enums.py
pymatviz/histogram.py
pymatviz/io.py
pymatviz/keys.yml
pymatviz/notebook.py
pymatviz/phonons/__init__.py
pymatviz/phonons/figures.py
pymatviz/phonons/helpers.py
pymatviz/powerups.py
pymatviz/process_data.py
pymatviz/ptable/__init__.py
pymatviz/ptable/figures.py
pymatviz/py.typed
pymatviz/rainclouds.py
pymatviz/rdf/__init__.py
pymatviz/rdf/figures.py
pymatviz/rdf/helpers.py
pymatviz/sankey.py
pymatviz/scatter.py
pymatviz/structure/__init__.py
pymatviz/structure/figures.py
pymatviz/structure/helpers.py
pymatviz/sunburst/__init__.py
pymatviz/sunburst/chem_env.py
pymatviz/sunburst/chem_sys.py
pymatviz/sunburst/helpers.py
pymatviz/sunburst/spacegroup.py
pymatviz/templates.py
pymatviz/treemap/__init__.py
pymatviz/treemap/chem_env.py
pymatviz/treemap/chem_sys.py
pymatviz/treemap/py_pkg.py
pymatviz/typing.py
pymatviz/uncertainty.py
pymatviz/utils/__init__.py
pymatviz/utils/data.py
pymatviz/utils/plotting.py
pymatviz/utils/testing.py
pymatviz/widgets/.DS_Store
pymatviz/widgets/__init__.py
pymatviz/widgets/composition.py
pymatviz/widgets/matterviz.py
pymatviz/widgets/mime.py
pymatviz/widgets/structure.py
pymatviz/widgets/trajectory.py
pymatviz/xrd.py
pymatviz-0.17.3.dist-info/WHEEL
pymatviz-0.17.3.dist-info/METADATA
pymatviz-0.17.3.dist-info/RECORD
