Metadata-Version: 2.3
Name: pymatviz
Version: 0.17.3
Summary: A toolkit for visualizations in materials informatics
Keywords: chemistry,crystallography,data analysis,data visualization,materials informatics,plotly
Author: Janosh Riebesell
Author-email: Janosh Riebesell <janosh.riebesell@gmail.com>
License: MIT License
Classifier: License :: OSI Approved :: MIT License
Classifier: Programming Language :: Python :: 3 :: Only
Classifier: Programming Language :: Python :: 3.11
Classifier: Programming Language :: Python :: 3.12
Classifier: Programming Language :: Python :: 3.13
Classifier: Programming Language :: Python :: 3.14
Requires-Dist: anywidget>=0.9.18
Requires-Dist: kaleido>=1.2.0
Requires-Dist: moyopy[interface]>=0.7.1
Requires-Dist: nbformat>=5.10
Requires-Dist: numpy>=2
Requires-Dist: pandas[output-formatting,xml]>=2.2
Requires-Dist: plotly>=6.4
Requires-Dist: pymatgen>=2025.10.7
Requires-Dist: pyyaml>=6
Requires-Dist: scikit-learn>=1.5
Requires-Dist: scipy>=1.14
Requires-Dist: seekpath>=2.1 ; extra == 'brillouin'
Requires-Dist: matminer>=0.9 ; extra == 'cluster'
Requires-Dist: pdfcropmargins>=2 ; extra == 'df-pdf-export'
Requires-Dist: weasyprint>=60 ; extra == 'df-pdf-export'
Requires-Dist: bs4>=0.0.2 ; extra == 'df-svg-export'
Requires-Dist: cssutils>=2.9 ; extra == 'df-svg-export'
Requires-Dist: lxml>=4.9 ; extra == 'df-svg-export'
Requires-Dist: jupyter>=1.1 ; extra == 'gh-pages'
Requires-Dist: lazydocs>=0.4 ; extra == 'gh-pages'
Requires-Dist: nbconvert>=7.16 ; extra == 'gh-pages'
Requires-Dist: matminer>=0.9 ; extra == 'make-assets'
Requires-Dist: phonopy>=2.31 ; extra == 'phonons'
Requires-Dist: pymatviz[df-pdf-export,df-svg-export,cluster,phonons] ; extra == 'test'
Requires-Dist: pytest-cov>=6 ; extra == 'test'
Requires-Dist: pytest-split>=0.9 ; extra == 'test'
Requires-Dist: pytest>=8 ; extra == 'test'
Requires-Dist: umap-learn>=0.5 ; python_full_version < '3.13' and extra == 'umap'
Requires-Python: >=3.11
Project-URL: Homepage, https://github.com/janosh/pymatviz
Provides-Extra: brillouin
Provides-Extra: cluster
Provides-Extra: df-pdf-export
Provides-Extra: df-svg-export
Provides-Extra: gh-pages
Provides-Extra: make-assets
Provides-Extra: phonons
Provides-Extra: test
Provides-Extra: umap
